CHANGELOG.txt
LICENSE.txt
MANIFEST.in
README.txt
setup.cfg
setup.py
RecordConvert.egg-info/PKG-INFO
RecordConvert.egg-info/SOURCES.txt
RecordConvert.egg-info/dependency_links.txt
RecordConvert.egg-info/entry_points.txt
RecordConvert.egg-info/not-zip-safe
RecordConvert.egg-info/requires.txt
RecordConvert.egg-info/top_level.txt
doc/index.txt
doc/source/api.rst
doc/source/conf.py
doc/source/index.rst
doc/source/manual.rst
recordconvert/__init__.py
recordconvert/reserved.py
test/README.txt
test/doc.py