Metadata-Version: 1.0
Name: RecordConvert
Version: 0.1.3
Summary: Tools for handling nested sets of records of the type you might encounter frequently when dealing with relational database management systems. Includes tools for working with the Repeatable Nested Records data model. Built on ConversionKit.
Home-page: http://jimmyg.org/work/code/recordconvert/index.html
Author: James Gardner
Author-email: UNKNOWN
License: GNU AGPLv3
Platform: UNKNOWN
